exoorbit/__init__.py
exoorbit/_version.py
exoorbit/bodies.py
exoorbit/database.py
exoorbit/dataclasses_quantity.py
exoorbit/library.py
exoorbit/orbit.py
exoorbit/util.py
exoorbit-0.1.20.dist-info/METADATA
exoorbit-0.1.20.dist-info/WHEEL
exoorbit-0.1.20.dist-info/top_level.txt
exoorbit-0.1.20.dist-info/RECORD
