Metadata-Version: 2.1
Name: exoorbit
Version: 0.1.20
Summary: UNKNOWN
Home-page: https://github.com/AWehrhahn/ExoOrbits
Author: Ansgar Wehrhahn
Author-email: ansgar.wehrhahn@physics.uu.se
License: UNKNOWN
Platform: UNKNOWN
